_cvxcore.cp39-win_amd64.pyd
_cvxpy_sparsecholesky.cp39-win_amd64.pyd
cvxpy/__init__.py
cvxpy/error.py
cvxpy/py.typed
cvxpy/settings.py
cvxpy/version.py
cvxpy/atoms/__init__.py
cvxpy/atoms/atom.py
cvxpy/atoms/axis_atom.py
cvxpy/atoms/condition_number.py
cvxpy/atoms/cummax.py
cvxpy/atoms/cumprod.py
cvxpy/atoms/cvar.py
cvxpy/atoms/dist_ratio.py
cvxpy/atoms/dotsort.py
cvxpy/atoms/errormsg.py
cvxpy/atoms/eye_minus_inv.py
cvxpy/atoms/gen_lambda_max.py
cvxpy/atoms/geo_mean.py
cvxpy/atoms/gmatmul.py
cvxpy/atoms/harmonic_mean.py
cvxpy/atoms/inv_prod.py
cvxpy/atoms/lambda_max.py
cvxpy/atoms/lambda_min.py
cvxpy/atoms/lambda_sum_largest.py
cvxpy/atoms/lambda_sum_smallest.py
cvxpy/atoms/length.py
cvxpy/atoms/log_det.py
cvxpy/atoms/log_sum_exp.py
cvxpy/atoms/matrix_frac.py
cvxpy/atoms/max.py
cvxpy/atoms/min.py
cvxpy/atoms/mixed_norm.py
cvxpy/atoms/norm.py
cvxpy/atoms/norm1.py
cvxpy/atoms/norm_inf.py
cvxpy/atoms/norm_nuc.py
cvxpy/atoms/one_minus_pos.py
cvxpy/atoms/perspective.py
cvxpy/atoms/pf_eigenvalue.py
cvxpy/atoms/pnorm.py
cvxpy/atoms/prod.py
cvxpy/atoms/ptp.py
cvxpy/atoms/quad_form.py
cvxpy/atoms/quad_over_lin.py
cvxpy/atoms/sigma_max.py
cvxpy/atoms/sign.py
cvxpy/atoms/stats.py
cvxpy/atoms/sum_largest.py
cvxpy/atoms/sum_smallest.py
cvxpy/atoms/sum_squares.py
cvxpy/atoms/suppfunc.py
cvxpy/atoms/total_variation.py
cvxpy/atoms/tr_inv.py
cvxpy/atoms/von_neumann_entr.py
cvxpy/atoms/affine/__init__.py
cvxpy/atoms/affine/add_expr.py
cvxpy/atoms/affine/affine_atom.py
cvxpy/atoms/affine/binary_operators.py
cvxpy/atoms/affine/bmat.py
cvxpy/atoms/affine/conj.py
cvxpy/atoms/affine/conv.py
cvxpy/atoms/affine/cumsum.py
cvxpy/atoms/affine/diag.py
cvxpy/atoms/affine/diff.py
cvxpy/atoms/affine/hstack.py
cvxpy/atoms/affine/imag.py
cvxpy/atoms/affine/index.py
cvxpy/atoms/affine/kron.py
cvxpy/atoms/affine/partial_trace.py
cvxpy/atoms/affine/partial_transpose.py
cvxpy/atoms/affine/promote.py
cvxpy/atoms/affine/real.py
cvxpy/atoms/affine/reshape.py
cvxpy/atoms/affine/sum.py
tyba_cvxpy-1.6.0.dist-info/LICENSE
tyba_cvxpy-1.6.0.dist-info/METADATA
tyba_cvxpy-1.6.0.dist-info/WHEEL
tyba_cvxpy-1.6.0.dist-info/top_level.txt
tyba_cvxpy-1.6.0.dist-info/RECORD
