Metadata-Version: 2.1
Name: tyba-cvxpy
Version: 1.6.0
Summary: A domain-specific language for modeling convex optimization problems in Python.
Author-email: Steven Diamond <stevend2@stanford.edu>, akshayka@cs.stanford.edu, Eric Chu <echu508@stanford.edu>, Stephen Boyd <boyd@stanford.edu>
License: Apache License, Version 2.0
Project-URL: Homepage, https://github.com/cvxpy/cvxpy
Requires-Python: >=3.9
License-File: LICENSE
Requires-Dist: osqp>=0.6.2
Requires-Dist: clarabel>=0.5.0
Requires-Dist: scs>=3.2.4.post1
Requires-Dist: numpy>=1.20
Requires-Dist: scipy>=1.1.0
Provides-Extra: cbc
Requires-Dist: cylp>=0.91.5; extra == "cbc"
Provides-Extra: clarabel
Provides-Extra: cvxopt
Requires-Dist: cvxopt; extra == "cvxopt"
Provides-Extra: daqp
Requires-Dist: daqp; extra == "daqp"
Provides-Extra: diffcp
Requires-Dist: diffcp; extra == "diffcp"
Provides-Extra: ecos
Requires-Dist: ecos; extra == "ecos"
Provides-Extra: ecos_bb
Requires-Dist: ecos; extra == "ecos-bb"
Provides-Extra: glop
Requires-Dist: ortools<9.10,>=9.7; extra == "glop"
Provides-Extra: glpk
Requires-Dist: cvxopt; extra == "glpk"
Provides-Extra: glpk_mi
Requires-Dist: cvxopt; extra == "glpk-mi"
Provides-Extra: gurobi
Requires-Dist: gurobipy; extra == "gurobi"
Provides-Extra: highs
Requires-Dist: highspy; extra == "highs"
Provides-Extra: mosek
Requires-Dist: Mosek; extra == "mosek"
Provides-Extra: osqp
Provides-Extra: pdlp
Requires-Dist: ortools<9.10,>=9.7; extra == "pdlp"
Provides-Extra: piqp
Requires-Dist: piqp; extra == "piqp"
Provides-Extra: proxqp
Requires-Dist: proxsuite; extra == "proxqp"
Provides-Extra: scip
Requires-Dist: PySCIPOpt; extra == "scip"
Provides-Extra: scipy
Requires-Dist: scipy; extra == "scipy"
Provides-Extra: scs
Requires-Dist: setuptools>65.5.1; extra == "scs"
Provides-Extra: xpress
Requires-Dist: xpress; extra == "xpress"
Provides-Extra: doc
Requires-Dist: sphinx; extra == "doc"
Requires-Dist: sphinxcontrib.jquery; extra == "doc"
Requires-Dist: sphinx-inline-tabs; extra == "doc"
Requires-Dist: sphinx-design; extra == "doc"
Requires-Dist: sphinx-immaterial>=0.11.7; extra == "doc"
Provides-Extra: testing
Requires-Dist: pytest; extra == "testing"
Requires-Dist: hypothesis; extra == "testing"
